sdv/__init__.py
sdv/codes.py
sdv/errors.py
sdv/utils.py
sdv/version.py
sdv/xmlconst.py
sdv/resources/__init__.py
sdv/resources/xsd/stix_1.0/campaign.xsd
sdv/resources/xsd/stix_1.0/course_of_action.xsd
sdv/resources/xsd/stix_1.0/data_marking.xsd
sdv/resources/xsd/stix_1.0/exploit_target.xsd
sdv/resources/xsd/stix_1.0/incident.xsd
sdv/resources/xsd/stix_1.0/indicator.xsd
sdv/resources/xsd/stix_1.0/stix_common.xsd
sdv/resources/xsd/stix_1.0/stix_core.xsd
sdv/resources/xsd/stix_1.0/stix_default_vocabularies.xsd
sdv/resources/xsd/stix_1.0/threat_actor.xsd
sdv/resources/xsd/stix_1.0/ttp.xsd
sdv/resources/xsd/stix_1.0/cybox/cybox_common.xsd
sdv/resources/xsd/stix_1.0/cybox/cybox_core.xsd
sdv/resources/xsd/stix_1.0/cybox/cybox_default_vocabularies.xsd
sdv/resources/xsd/stix_1.0/cybox/extensions/platform/cpe2.3.xsd
sdv/resources/xsd/stix_1.0/cybox/objects/API_Object.xsd
sdv/resources/xsd/stix_1.0/cybox/objects/Account_Object.xsd
sdv/resources/xsd/stix_1.0/cybox/objects/Address_Object.xsd
sdv/resources/xsd/stix_1.0/cybox/objects/Artifact_Object.xsd
sdv/resources/xsd/stix_1.0/cybox/objects/Code_Object.xsd
sdv/resources/xsd/stix_1.0/cybox/objects/Custom_Object.xsd
sdv/resources/xsd/stix_1.0/cybox/objects/DNS_Cache_Object.xsd
sdv/resources/xsd/stix_1.0/cybox/objects/DNS_Query_Object.xsd
sdv/resources/xsd/stix_1.0/cybox/objects/DNS_Record_Object.xsd
sdv/resources/xsd/stix_1.0/cybox/objects/Device_Object.xsd
sdv/resources/xsd/stix_1.0/cybox/objects/Disk_Object.xsd
sdv/resources/xsd/stix_1.0/cybox/objects/Disk_Partition_Object.xsd
sdv/resources/xsd/stix_1.0/cybox/objects/Email_Message_Object.xsd
sdv/resources/xsd/stix_1.0/cybox/objects/File_Object.xsd
sdv/resources/xsd/stix_1.0/cybox/objects/GUI_Dialogbox_Object.xsd
sdv/resources/xsd/stix_1.0/cybox/objects/GUI_Object.xsd
sdv/resources/xsd/stix_1.0/cybox/objects/GUI_Window_Object.xsd
sdv/resources/xsd/stix_1.0/cybox/objects/HTTP_Session_Object.xsd
sdv/resources/xsd/stix_1.0/cybox/objects/Library_Object.xsd
stix_validator-3.0.0.dist-info/LICENSE.txt
stix_validator-3.0.0.dist-info/METADATA
stix_validator-3.0.0.dist-info/WHEEL
stix_validator-3.0.0.dist-info/entry_points.txt
stix_validator-3.0.0.dist-info/top_level.txt
stix_validator-3.0.0.dist-info/RECORD
