Metadata-Version: 2.1
Name: stix-validator
Version: 3.0.0
Summary: APIs and scripts for validating STIX and CybOX documents.
Home-page: http://stix.mitre.org/
Author: The MITRE Corporation
Author-email: stix@mitre.org
License: UNKNOWN
Keywords: stix cybox xml validation validator stix-validator
Platform: UNKNOWN
Classifier: Development Status :: 5 - Production/Stable
Classifier: Intended Audience :: Developers
Classifier: License :: OSI Approved :: BSD License
Classifier: Operating System :: OS Independent
Classifier: Programming Language :: Python :: 3.8
Classifier: Programming Language :: Python :: 3.9
Classifier: Programming Language :: Python :: 3.10
Classifier: Programming Language :: Python :: 3.11
Classifier: Programming Language :: Python :: 3.12
Requires-Dist: xlrd (>=0.9.2)
Requires-Dist: ordereddict
Requires-Dist: python-dateutil
Requires-Dist: packaging
Requires-Dist: lxml (>=3.3.5)
Requires-Dist: setuptools
Provides-Extra: docs
Requires-Dist: Sphinx (==1.3.1) ; extra == 'docs'
Requires-Dist: sphinx-rtd-theme (==0.1.8) ; extra == 'docs'
Provides-Extra: test
Requires-Dist: bumpversion ; extra == 'test'
Requires-Dist: pytest ; extra == 'test'
Requires-Dist: tox ; extra == 'test'
